{
  "id": 10,
  "file": "bacta",
  "type": "DRUGS",
  "name_en": "Bacta",
  "name_fr": "Bacta",
  "name_es": "Bacta",
  "dismantable": false,
  "is_heavy": false,
  "is_personal": false,
  "is_stackable": true,
  "can_drop": true,
  "can_hide": true,
  "can_move": true,
  "can_be_destroyed_by_fire": false,
  "can_be_broken_by_fire": true,
  "description_en": "One cannot be entirely sure what it is exactly, but there's one way to find out. Swallow it !",
  "examine_text_en": "Eat me!.",
  "description_fr": "On ne sait pas vraiment ce que c'est...\nUn seul moyen pour s'en assurer, l'avaler !",
  "examine_text_fr": "Mangez-moi."
}
